{"assets":{"C8FB0B10C9BC7C808D7FDE56107AE248":{"type":"texture","index":44,"assetRequest":{"type":"slide","state":"outgoing","slide":"5CA2723A-84D9-4D6A-918B-A42B088A741D"},"url":"assets/C8FB0B10C9BC7C808D7FDE56107AE248.svg","width":720,"height":540},"81B18F088CCA0B60BF5394FA398F6216":{"type":"texture","index":45,"assetRequest":{"type":"slide","state":"incoming","slide":"5796BE3F-4EB9-4492-874C-BB5EFF7AE355"},"url":"assets/81B18F088CCA0B60BF5394FA398F6216.svg","width":720,"height":540}},"events":[{"effects":[{"beginTime":0,"baseLayer":{"animations":[],"initialState":{"affineTransform":[1,0,0,1,0,0],"masksToBounds":true,"rotation":0,"scale":1,"position":{"pointX":360,"pointY":270},"width":720,"sublayerTransform":[1,0,0,0,0,1,0,0,0,0,1,0,0,0,0,1],"contentsRect":{"y":0,"x":0,"width":1,"height":1},"opacity":1,"edgeAntialiasingMask":0,"height":540,"hidden":false,"anchorPoint":{"pointX":0.5,"pointY":0.5}},"objectID":"0","layers":[{"animations":[],"initialState":{"affineTransform":[1,0,0,1,0,0],"masksToBounds":false,"rotation":0,"scale":1,"position":{"pointX":360,"pointY":270},"width":720,"sublayerTransform":[1,0,0,0,0,1,0,0,0,0,1,-0.0007001582493355197,0,0,0,1],"contentsRect":{"y":0,"x":0,"width":1,"height":1},"opacity":1,"edgeAntialiasingMask":15,"height":540,"hidden":false,"anchorPoint":{"pointX":0.5,"pointY":0.5}},"layers":[{"animations":[],"layers":[],"initialState":{"affineTransform":[1,0,0,1,0,0],"masksToBounds":false,"rotation":0,"scale":1,"position":{"pointX":360,"pointY":270},"width":720,"sublayerTransform":[1,0,0,0,0,1,0,0,0,0,1,0,0,0,0,1],"contentsRect":{"y":0,"x":0,"width":1,"height":1},"opacity":1,"edgeAntialiasingMask":0,"height":540,"hidden":false,"anchorPoint":{"pointX":0.5,"pointY":0.5}},"texture":"81B18F088CCA0B60BF5394FA398F6216"},{"animations":[{"from":{"scalar":false},"beginTime":0,"repeatCount":0,"fillMode":"both","property":"hidden","duration":0.01,"to":{"scalar":true}}],"layers":[],"initialState":{"affineTransform":[1,0,0,1,0,0],"masksToBounds":false,"rotation":0,"scale":1,"position":{"pointX":360,"pointY":270},"width":720,"sublayerTransform":[1,0,0,0,0,1,0,0,0,0,1,0,0,0,0,1],"contentsRect":{"y":0,"x":0,"width":1,"height":1},"opacity":1,"edgeAntialiasingMask":0,"height":540,"hidden":false,"anchorPoint":{"pointX":0.5,"pointY":0.5}},"texture":"C8FB0B10C9BC7C808D7FDE56107AE248"}]}]},"effects":[],"duration":0.01,"type":"transition","name":"none","objectID":"0"}],"automaticPlay":false,"hyperlinks":[{"url":"http://osgug.ucaiug.org/sgsystems/OpenADE/Shared%20Documents/Testing%20and%20Certification/GreenButtonTestPlan/referenceMaterial/GreenButtonAuthorization.docx","targetRectangle":{"y":486.9421936697472,"x":81.59999781886376,"width":249.0390625,"height":17.4765625}},{"url":"http://osgug.ucaiug.org/sgsystems/OpenADE/Shared%20Documents/Testing%20and%20Certification/GreenButtonTestPlan/OpenADE_2014_Notes/GreenButtonCMDWorkshop20140513.pptx","targetRectangle":{"y":486.94219356642,"x":375.5999984580513,"width":261.9736328124999,"height":15.5419921875}}],"accessibility":[{"text":"Example Scope Strings (* subject to change)","targetRectangle":{"y":79.22496618391028,"x":30.1515611944717,"width":386.7600041985512,"height":26.24625014550983}},{"text":"SCE(*)","targetRectangle":{"y":106.2249663518836,"x":61.83156061613636,"width":52.98437540251761,"height":25.97987520136682}},{"text":"Scope = “FB=1_3_4_5_8_13_18_19_31_34_35_39;\u2028IntervalDuration=900_3600;BlockDuration=Daily; HistoryLength= 34128000;SubscriptionFrequency=Daily;\u2028 AccountCollection=5;BR=1;”","targetRectangle":{"y":132.83296657197,"x":93.51156005823691,"width":487.64765625,"height":79.38289358921051}},{"text":"PG&E(*)","targetRectangle":{"y":212.7497664111806,"x":61.83156061613636,"width":66.85937540251763,"height":25.97987520136684}},{"text":"Scope = “FB=1_3_4_5_7_8_13_14_15_18_19_31_32_34_35_37_38_39_40;\u2028IntervalDuration=300_900_3600;BlockDuration=Daily_BillingPeriod_Weekly_Monthly; HistoryLength=63072000;SubscriptionFrequency=Daily;\u2028 AccountCollection=5;BR=1;”","targetRectangle":{"y":239.357766631267,"x":93.51156005823691,"width":607.56140625,"height":81.6132938220978}},{"text":"SDG&E(*)","targetRectangle":{"y":321.5049667033647,"x":61.83156061613636,"width":80.72500040251762,"height":25.97987520136684}},{"text":"Scope = “FB=1_3_4_5_8_13_14_18_19_31_34_35_39_40;\u2028IntervalDuration=300_900_3600;BlockDuration=Daily_BillingPeriod_Weekly_Monthly; HistoryLength=94608000;SubscriptionFrequency=Daily;\u2028 AccountCollection=5;BR=1;”","targetRectangle":{"y":348.1129669234512,"x":93.51156005823691,"width":607.56140625,"height":79.38289358921054}},{"text":"Examples for Connect My Data","targetRectangle":{"y":18.59999990463257,"x":66.56424789744091,"width":528.134765625,"height":40.822265625}},{"text":"Ref: Authorization.docx Section 2.6","targetRectangle":{"y":486.9421936697472,"x":81.59999781886376,"width":249.0390625,"height":17.4765625}},{"text":"Ref: GreenButtonCMDWorkshop: Slide 04","targetRectangle":{"y":486.94219356642,"x":375.5999984580513,"width":261.9736328124999,"height":15.5419921875}},{"text":"image2.gif","targetRectangle":{"y":0,"x":666,"width":48,"height":58.31251907348633}}],"baseLayer":{"animations":[],"initialState":{"affineTransform":[1,0,0,1,0,0],"masksToBounds":true,"rotation":0,"scale":1,"position":{"pointX":360,"pointY":270},"width":720,"sublayerTransform":[1,0,0,0,0,1,0,0,0,0,1,0,0,0,0,1],"contentsRect":{"y":0,"x":0,"width":1,"height":1},"opacity":1,"edgeAntialiasingMask":0,"height":540,"hidden":false,"anchorPoint":{"pointX":0.5,"pointY":0.5}},"objectID":"0","layers":[{"animations":[],"initialState":{"affineTransform":[1,0,0,1,0,0],"masksToBounds":false,"rotation":0,"scale":1,"position":{"pointX":360,"pointY":270},"width":720,"sublayerTransform":[1,0,0,0,0,1,0,0,0,0,1,-0.0007001582493355197,0,0,0,1],"contentsRect":{"y":0,"x":0,"width":1,"height":1},"opacity":1,"edgeAntialiasingMask":15,"height":540,"hidden":false,"anchorPoint":{"pointX":0.5,"pointY":0.5}},"layers":[{"animations":[],"layers":[],"initialState":{"affineTransform":[1,0,0,1,0,0],"masksToBounds":false,"rotation":0,"scale":1,"position":{"pointX":360,"pointY":270},"width":720,"sublayerTransform":[1,0,0,0,0,1,0,0,0,0,1,0,0,0,0,1],"contentsRect":{"y":0,"x":0,"width":1,"height":1},"opacity":1,"edgeAntialiasingMask":0,"height":540,"hidden":false,"anchorPoint":{"pointX":0.5,"pointY":0.5}},"texture":"C8FB0B10C9BC7C808D7FDE56107AE248"}]}]}}]}